git_command/__init__.py
git_command-0.0.1.dist-info/LICENSE
git_command-0.0.1.dist-info/METADATA
git_command-0.0.1.dist-info/WHEEL
git_command-0.0.1.dist-info/RECORD
